alexgalt_framework/__init__.py
alexgalt_framework/api.py
alexgalt_framework/middleware.py
alexgalt_framework/orm.py
alexgalt_framework/response.py
alexeygalt_framework-0.0.2.1.dist-info/METADATA
alexeygalt_framework-0.0.2.1.dist-info/WHEEL
alexeygalt_framework-0.0.2.1.dist-info/top_level.txt
alexeygalt_framework-0.0.2.1.dist-info/RECORD
