Metadata-Version: 2.1
Name: alexeygalt_framework
Version: 0.0.2.1
Summary: Alexgalt Python Web Framework built for learning purposes.
Author: Alexey Shishkin
Author-email: alexeygalt@gmail.com
License: MIT
Classifier: Programming Language :: Python :: 3.11
Requires-Python: >=3.11.0
Requires-Dist: Jinja2==3.1.4
Requires-Dist: parse==1.20.2
Requires-Dist: requests==2.32.3
Requires-Dist: requests-wsgi-adapter==0.4.1
Requires-Dist: WebOb==1.8.8
Requires-Dist: whitenoise==6.7.0
